[{"3.96": "https://media0.giphy.com/media/Jt219Ftr1heAE/giphy.gif"}, {"4.2": "https://media2.giphy.com/media/BpwhSRuEi18w8/giphy.gif"}, {"1.879999999999999": "https://media2.giphy.com/media/26BGHw7WClura6YkE/giphy.gif"}, {"7.120000000000001": "https://media1.giphy.com/media/kTDTS6JlCxRWE/giphy.gif"}, {"3.0": "https://media2.giphy.com/media/rVGIaPNWOuqwE/giphy.gif"}, {"4.640000000000001": "https://media3.giphy.com/media/yYxYZ8et9kb8k/giphy.gif"}, {"2.719999999999999": "https://media3.giphy.com/media/hZlquGV8qrao0/giphy.gif"}, {"2.080000000000002": "https://media3.giphy.com/media/sSRm3HxYdMwow/giphy.gif"}, {"1.3999999999999986": "https://media0.giphy.com/media/j17lYSZ61u6KA/giphy.gif"}, {"1.2800000000000011": "https://media3.giphy.com/media/M2AkfVYQ7lkEU/giphy.gif"}, {"5.079999999999998": "https://media0.giphy.com/media/j17lYSZ61u6KA/giphy.gif"}, {"1.5200000000000031": "https://media2.giphy.com/media/IHkWN6nXpl7HO/giphy.gif"}, {"1.1599999999999966": "https://media0.giphy.com/media/KnOX6nlcJH7he/giphy.gif"}, {"5.039999999999999": "https://media2.giphy.com/media/TNVXV3piYixEs/giphy.gif"}, {"6.600000000000001": "https://media2.giphy.com/media/l673cYwNZE1iM/giphy.gif"}, {"10.560000000000002": "https://media0.giphy.com/media/TikxJHJxVZz4Q/giphy.gif"}, {"5.039999999999999": "https://media0.giphy.com/media/l0HlGltoQfMUrtpug/giphy.gif"}, {"6.319999999999993": "https://media3.giphy.com/media/sSRm3HxYdMwow/giphy.gif"}, {"2.6400000000000006": "https://media2.giphy.com/media/WtMqSY52YDFfO/giphy.gif"}, {"1.4000000000000057": "https://media2.giphy.com/media/GLXH3AHtPqmty/giphy.gif"}, {"2.8799999999999955": "https://media0.giphy.com/media/pLYUuYFru7kFW/giphy.gif"}, {"2.240000000000009": "https://media2.giphy.com/media/MYFElCBOOLc0E/giphy.gif"}, {"1.559999999999988": "https://media0.giphy.com/media/wjTBn1ECUjLzy/giphy.gif"}, {"0.3200000000000074": "https://media0.giphy.com/media/htCURM05evPkk/giphy.gif"}, {"2.480000000000004": "https://media2.giphy.com/media/IHkWN6nXpl7HO/giphy.gif"}, {"2.6799999999999926": "https://media3.giphy.com/media/UzwINQTulNNio/giphy.gif"}, {"6.960000000000008": "https://media3.giphy.com/media/sSRm3HxYdMwow/giphy.gif"}, {"2.6799999999999926": "https://media0.giphy.com/media/j17lYSZ61u6KA/giphy.gif"}, {"1.1200000000000045": "https://media3.giphy.com/media/l2YWBMGxVZhGNVT9K/giphy.gif"}, {"2.200000000000003": "https://media3.giphy.com/media/sSRm3HxYdMwow/giphy.gif"}, {"13.399999999999991": "https://media0.giphy.com/media/dLlO8K9goseNa/giphy.gif"}, {"17.24000000000001": "https://media3.giphy.com/media/6dKLh7k3t3cB2/giphy.gif"}, {"2.799999999999983": "https://media0.giphy.com/media/lMzaVrGwYGpG0/giphy.gif"}, {"52.28": "https://media1.giphy.com/media/b1IakIOU3Hdmw/giphy.gif"}]